[{"tags": [], "wantsTranslation": false, "totalSubmit": 477, "totalAccepted": 295, "flag": 5, "pid": "CF1556F", "title": "Sports Betting", "difficulty": 6, "fullScore": 100, "type": "CF"}, {"tags": [], "wantsTranslation": false, "totalSubmit": 407, "totalAccepted": 123, "flag": 5, "pid": "CF1556G", "title": "Gates to Another World", "difficulty": 7, "fullScore": 100, "type": "CF"}, {"tags": [], "wantsTranslation": false, "totalSubmit": 341, "totalAccepted": 102, "flag": 5, "pid": "CF1556H", "title": "DIY Tree", "difficulty": 7, "fullScore": 100, "type": "CF"}, {"tags": [], "wantsTranslation": false, "totalSubmit": 808, "totalAccepted": 336, "flag": 5, "pid": "CF1557A", "title": "Ezzat and Two Subsequences", "difficulty": 1, "fullScore": 100, "type": "CF"}, {"tags": [], "wantsTranslation": false, "totalSubmit": 523, "totalAccepted": 273, "flag": 5, "pid": "CF1557B", "title": "Moamen and k-subarrays", "difficulty": 2, "fullScore": 100, "type": "CF"}, {"tags": [], "wantsTranslation": false, "totalSubmit": 722, "totalAccepted": 383, "flag": 5, "pid": "CF1557C", "title": "Moamen and XOR", "difficulty": 4, "fullScore": 100, "type": "CF"}, {"tags": [], "wantsTranslation": false, "totalSubmit": 807, "totalAccepted": 299, "flag": 5, "pid": "CF1557D", "title": "Ezzat and Grid", "difficulty": 5, "fullScore": 100, "type": "CF"}, {"tags": [], "wantsTranslation": false, "totalSubmit": 449, "totalAccepted": 133, "flag": 5, "pid": "CF1557E", "title": "Assiut Chess", "difficulty": 6, "fullScore": 100, "type": "CF"}, {"tags": [], "wantsTranslation": false, "totalSubmit": 292, "totalAccepted": 221, "flag": 5, "pid": "CF1558A", "title": "Charmed by the Game", "difficulty": 3, "fullScore": 100, "type": "CF"}, {"tags": [], "wantsTranslation": false, "totalSubmit": 870, "totalAccepted": 486, "flag": 5, "pid": "CF1558B", "title": "Up the Strip", "difficulty": 4, "fullScore": 100, "type": "CF"}, {"tags": [], "wantsTranslation": false, "totalSubmit": 754, "totalAccepted": 369, "flag": 5, "pid": "CF1558C", "title": "Bottom-Tier Reversals", "difficulty": 4, "fullScore": 100, "type": "CF"}, {"tags": [42, 45, 50, 252], "wantsTranslation": false, "totalSubmit": 527, "totalAccepted": 217, "flag": 5, "pid": "CF1558D", "title": "Top-Notch Insertions", "difficulty": 6, "fullScore": 100, "type": "CF"}, {"tags": [], "wantsTranslation": false, "totalSubmit": 435, "totalAccepted": 198, "flag": 5, "pid": "CF1558E", "title": "Down Below", "difficulty": 7, "fullScore": 100, "type": "CF"}, {"tags": [], "wantsTranslation": false, "totalSubmit": 356, "totalAccepted": 192, "flag": 5, "pid": "CF1558F", "title": "Strange Sort", "difficulty": 7, "fullScore": 100, "type": "CF"}, {"tags": [], "wantsTranslation": false, "totalSubmit": 662, "totalAccepted": 361, "flag": 5, "pid": "CF1559A", "title": "Mocha and Math", "difficulty": 1, "fullScore": 100, "type": "CF"}, {"tags": [], "wantsTranslation": false, "totalSubmit": 416, "totalAccepted": 270, "flag": 5, "pid": "CF1559B", "title": "Mocha and Red and Blue", "difficulty": 2, "fullScore": 100, "type": "CF"}, {"tags": [], "wantsTranslation": false, "totalSubmit": 582, "totalAccepted": 322, "flag": 5, "pid": "CF1559C", "title": "Mocha and Hiking", "difficulty": 3, "fullScore": 100, "type": "CF"}, {"tags": [], "wantsTranslation": false, "totalSubmit": 767, "totalAccepted": 540, "flag": 5, "pid": "CF1559D1", "title": "Mocha and Diana (Easy Version)", "difficulty": 4, "fullScore": 100, "type": "CF"}, {"tags": [], "wantsTranslation": false, "totalSubmit": 1132, "totalAccepted": 533, "flag": 5, "pid": "CF1559D2", "title": "Mocha and Diana (Hard Version)", "difficulty": 5, "fullScore": 100, "type": "CF"}, {"tags": [], "wantsTranslation": false, "totalSubmit": 491, "totalAccepted": 298, "flag": 5, "pid": "CF1559E", "title": "Mocha and Stars", "difficulty": 6, "fullScore": 100, "type": "CF"}, {"tags": [1], "wantsTranslation": false, "totalSubmit": 1105, "totalAccepted": 624, "flag": 5, "pid": "CF1560A", "title": "Dislike of Threes", "difficulty": 1, "fullScore": 100, "type": "CF"}, {"tags": [5], "wantsTranslation": false, "totalSubmit": 980, "totalAccepted": 525, "flag": 5, "pid": "CF1560B", "title": "Who's Opposite?", "difficulty": 2, "fullScore": 100, "type": "CF"}, {"tags": [], "wantsTranslation": false, "totalSubmit": 615, "totalAccepted": 403, "flag": 5, "pid": "CF1560C", "title": "Infinity Table", "difficulty": 2, "fullScore": 100, "type": "CF"}, {"tags": [], "wantsTranslation": false, "totalSubmit": 499, "totalAccepted": 300, "flag": 5, "pid": "CF1560D", "title": "Make a Power of Two", "difficulty": 3, "fullScore": 100, "type": "CF"}, {"tags": [], "wantsTranslation": false, "totalSubmit": 386, "totalAccepted": 207, "flag": 5, "pid": "CF1560E", "title": "Polycarp and String Transformation", "difficulty": 4, "fullScore": 100, "type": "CF"}, {"tags": [], "wantsTranslation": false, "totalSubmit": 560, "totalAccepted": 251, "flag": 5, "pid": "CF1560F1", "title": "Nearest Beautiful Number (easy version)", "difficulty": 4, "fullScore": 100, "type": "CF"}, {"tags": [], "wantsTranslation": false, "totalSubmit": 517, "totalAccepted": 279, "flag": 5, "pid": "CF1560F2", "title": "Nearest Beautiful Number (hard version)", "difficulty": 5, "fullScore": 100, "type": "CF"}, {"tags": [], "wantsTranslation": false, "totalSubmit": 622, "totalAccepted": 277, "flag": 5, "pid": "CF1561A", "title": "Simply Strange Sort", "difficulty": 1, "fullScore": 100, "type": "CF"}, {"tags": [7], "wantsTranslation": false, "totalSubmit": 632, "totalAccepted": 272, "flag": 5, "pid": "CF1561C", "title": "Deep Down Below", "difficulty": 3, "fullScore": 100, "type": "CF"}, {"tags": [5, 12], "wantsTranslation": false, "totalSubmit": 554, "totalAccepted": 377, "flag": 5, "pid": "CF1561D1", "title": "Up the Strip (simplified version)", "difficulty": 4, "fullScore": 100, "type": "CF"}, {"tags": [], "wantsTranslation": false, "totalSubmit": 532, "totalAccepted": 372, "flag": 5, "pid": "CF1562A", "title": "The Miracle and the Sleeper", "difficulty": 2, "fullScore": 100, "type": "CF"}, {"tags": [], "wantsTranslation": false, "totalSubmit": 401, "totalAccepted": 245, "flag": 5, "pid": "CF1562B", "title": "Scenes From a Memory", "difficulty": 2, "fullScore": 100, "type": "CF"}, {"tags": [], "wantsTranslation": false, "totalSubmit": 566, "totalAccepted": 269, "flag": 5, "pid": "CF1562C", "title": "Rings", "difficulty": 3, "fullScore": 100, "type": "CF"}, {"tags": [], "wantsTranslation": false, "totalSubmit": 343, "totalAccepted": 246, "flag": 5, "pid": "CF1562D1", "title": "Two Hundred Twenty One (easy version)", "difficulty": 4, "fullScore": 100, "type": "CF"}, {"tags": [], "wantsTranslation": false, "totalSubmit": 484, "totalAccepted": 200, "flag": 5, "pid": "CF1562D2", "title": "Two Hundred Twenty One (hard version)", "difficulty": 5, "fullScore": 100, "type": "CF"}, {"tags": [], "wantsTranslation": false, "totalSubmit": 669, "totalAccepted": 371, "flag": 5, "pid": "CF1562E", "title": "Rescue Niwen!", "difficulty": 5, "fullScore": 100, "type": "CF"}, {"tags": [], "wantsTranslation": false, "totalSubmit": 545, "totalAccepted": 125, "flag": 5, "pid": "CF1562F", "title": "Tubular Bells", "difficulty": 6, "fullScore": 100, "type": "CF"}, {"tags": [], "wantsTranslation": false, "totalSubmit": 599, "totalAccepted": 223, "flag": 5, "pid": "CF1566A", "title": "Median Maximization", "difficulty": 1, "fullScore": 100, "type": "CF"}, {"tags": [], "wantsTranslation": false, "totalSubmit": 303, "totalAccepted": 201, "flag": 5, "pid": "CF1566B", "title": "MIN-MEX Cut", "difficulty": 1, "fullScore": 100, "type": "CF"}, {"tags": [], "wantsTranslation": false, "totalSubmit": 374, "totalAccepted": 205, "flag": 5, "pid": "CF1566C", "title": "MAX-MEX Cut", "difficulty": 2, "fullScore": 100, "type": "CF"}, {"tags": [], "wantsTranslation": false, "totalSubmit": 261, "totalAccepted": 193, "flag": 5, "pid": "CF1566D1", "title": "Seating Arrangements (easy version)", "difficulty": 2, "fullScore": 100, "type": "CF"}, {"tags": [], "wantsTranslation": false, "totalSubmit": 195, "totalAccepted": 150, "flag": 5, "pid": "CF1566D2", "title": "Seating Arrangements (hard version)", "difficulty": 4, "fullScore": 100, "type": "CF"}, {"tags": [], "wantsTranslation": false, "totalSubmit": 346, "totalAccepted": 220, "flag": 5, "pid": "CF1566E", "title": "Buds Re-hanging", "difficulty": 5, "fullScore": 100, "type": "CF"}, {"tags": [], "wantsTranslation": false, "totalSubmit": 297, "totalAccepted": 127, "flag": 5, "pid": "CF1566F", "title": "Points Movement", "difficulty": 6, "fullScore": 100, "type": "CF"}, {"tags": [], "wantsTranslation": false, "totalSubmit": 268, "totalAccepted": 77, "flag": 5, "pid": "CF1566G", "title": "Four Vertices", "difficulty": 6, "fullScore": 100, "type": "CF"}, {"tags": [], "wantsTranslation": false, "totalSubmit": 74, "totalAccepted": 31, "flag": 5, "pid": "CF1566H", "title": "Xor-quiz", "difficulty": 7, "fullScore": 100, "type": "CF"}, {"tags": [], "wantsTranslation": false, "totalSubmit": 536, "totalAccepted": 339, "flag": 5, "pid": "CF1567A", "title": "Domino Disaster", "difficulty": 1, "fullScore": 100, "type": "CF"}, {"tags": [], "wantsTranslation": false, "totalSubmit": 527, "totalAccepted": 290, "flag": 5, "pid": "CF1567B", "title": "MEXor Mixup", "difficulty": 2, "fullScore": 100, "type": "CF"}, {"tags": [], "wantsTranslation": false, "totalSubmit": 492, "totalAccepted": 344, "flag": 5, "pid": "CF1567C", "title": "Carrying Conundrum", "difficulty": 3, "fullScore": 100, "type": "CF"}, {"tags": [], "wantsTranslation": false, "totalSubmit": 509, "totalAccepted": 252, "flag": 5, "pid": "CF1567D", "title": "Expression Evaluation Error", "difficulty": 4, "fullScore": 100, "type": "CF"}]