[{"tags": [], "wantsTranslation": false, "totalSubmit": 78, "totalAccepted": 25, "flag": 5, "pid": "CF802E", "title": "Marmots (medium)", "difficulty": 5, "fullScore": 100, "type": "CF"}, {"tags": [], "wantsTranslation": false, "totalSubmit": 47, "totalAccepted": 10, "flag": 5, "pid": "CF802F", "title": "Marmots (hard)", "difficulty": 6, "fullScore": 100, "type": "CF"}, {"tags": [1, 2, 111, 288], "wantsTranslation": false, "totalSubmit": 2633, "totalAccepted": 1052, "flag": 5, "pid": "CF802G", "title": "Fake News (easy)", "difficulty": 1, "fullScore": 100, "type": "CF"}, {"tags": [], "wantsTranslation": false, "totalSubmit": 205, "totalAccepted": 93, "flag": 5, "pid": "CF802H", "title": "Fake News (medium)", "difficulty": 6, "fullScore": 100, "type": "CF"}, {"tags": [], "wantsTranslation": false, "totalSubmit": 1663, "totalAccepted": 852, "flag": 5, "pid": "CF802I", "title": "Fake News (hard)", "difficulty": 6, "fullScore": 100, "type": "CF"}, {"tags": [], "wantsTranslation": false, "totalSubmit": 159, "totalAccepted": 77, "flag": 5, "pid": "CF802J", "title": "Send the Fool Further! (easy)", "difficulty": 3, "fullScore": 100, "type": "CF"}, {"tags": [], "wantsTranslation": false, "totalSubmit": 281, "totalAccepted": 112, "flag": 5, "pid": "CF802K", "title": "Send the Fool Further! (medium)", "difficulty": 5, "fullScore": 100, "type": "CF"}, {"tags": [], "wantsTranslation": false, "totalSubmit": 229, "totalAccepted": 133, "flag": 5, "pid": "CF802L", "title": "Send the Fool Further! (hard)", "difficulty": 6, "fullScore": 100, "type": "CF"}, {"tags": [], "wantsTranslation": false, "totalSubmit": 1221, "totalAccepted": 727, "flag": 5, "pid": "CF802M", "title": "April Fools' Problem (easy)", "difficulty": 3, "fullScore": 100, "type": "CF"}, {"tags": [], "wantsTranslation": false, "totalSubmit": 1106, "totalAccepted": 667, "flag": 5, "pid": "CF802N", "title": "April Fools' Problem (medium)", "difficulty": 6, "fullScore": 100, "type": "CF"}, {"tags": [], "wantsTranslation": false, "totalSubmit": 1495, "totalAccepted": 774, "flag": 5, "pid": "CF802O", "title": "April Fools' Problem (hard)", "difficulty": 6, "fullScore": 100, "type": "CF"}, {"tags": [7, 54], "wantsTranslation": false, "totalSubmit": 316, "totalAccepted": 107, "flag": 5, "pid": "CF803A", "title": "Maximal Binary Matrix", "difficulty": 3, "fullScore": 100, "type": "CF"}, {"tags": [], "wantsTranslation": false, "totalSubmit": 282, "totalAccepted": 118, "flag": 5, "pid": "CF803B", "title": "Distances to Zero", "difficulty": 2, "fullScore": 100, "type": "CF"}, {"tags": [], "wantsTranslation": false, "totalSubmit": 1535, "totalAccepted": 374, "flag": 5, "pid": "CF803C", "title": "Maximal GCD", "difficulty": 4, "fullScore": 100, "type": "CF"}, {"tags": [], "wantsTranslation": false, "totalSubmit": 400, "totalAccepted": 178, "flag": 5, "pid": "CF803D", "title": "Magazine Ad", "difficulty": 4, "fullScore": 100, "type": "CF"}, {"tags": [], "wantsTranslation": false, "totalSubmit": 413, "totalAccepted": 201, "flag": 5, "pid": "CF803E", "title": "Roma and Poker", "difficulty": 5, "fullScore": 100, "type": "CF"}, {"tags": [], "wantsTranslation": false, "totalSubmit": 660, "totalAccepted": 378, "flag": 5, "pid": "CF803F", "title": "Coprime Subsequences", "difficulty": 4, "fullScore": 100, "type": "CF"}, {"tags": [], "wantsTranslation": false, "totalSubmit": 1909, "totalAccepted": 608, "flag": 5, "pid": "CF803G", "title": "Periodic RMQ Problem", "difficulty": 6, "fullScore": 100, "type": "CF"}, {"tags": [], "wantsTranslation": false, "totalSubmit": 351, "totalAccepted": 214, "flag": 5, "pid": "CF804A", "title": "Find Amir", "difficulty": 3, "fullScore": 100, "type": "CF"}, {"tags": [], "wantsTranslation": false, "totalSubmit": 401, "totalAccepted": 239, "flag": 5, "pid": "CF804B", "title": "Minimum number of steps", "difficulty": 4, "fullScore": 100, "type": "CF"}, {"tags": [], "wantsTranslation": false, "totalSubmit": 182, "totalAccepted": 69, "flag": 5, "pid": "CF804C", "title": "Ice cream coloring", "difficulty": 5, "fullScore": 100, "type": "CF"}, {"tags": [213, 254, 270], "wantsTranslation": false, "totalSubmit": 788, "totalAccepted": 273, "flag": 5, "pid": "CF804D", "title": "Expected diameter of a tree", "difficulty": 6, "fullScore": 100, "type": "CF"}, {"tags": [], "wantsTranslation": false, "totalSubmit": 419, "totalAccepted": 129, "flag": 5, "pid": "CF804E", "title": "The same permutation ", "difficulty": 7, "fullScore": 100, "type": "CF"}, {"tags": [], "wantsTranslation": false, "totalSubmit": 234, "totalAccepted": 65, "flag": 5, "pid": "CF804F", "title": "Fake bullions", "difficulty": 7, "fullScore": 100, "type": "CF"}, {"tags": [239], "wantsTranslation": false, "totalSubmit": 545, "totalAccepted": 316, "flag": 5, "pid": "CF805A", "title": "Fake NP", "difficulty": 2, "fullScore": 100, "type": "CF"}, {"tags": [2, 318], "wantsTranslation": false, "totalSubmit": 853, "totalAccepted": 423, "flag": 5, "pid": "CF805B", "title": "3-palindrome", "difficulty": 2, "fullScore": 100, "type": "CF"}, {"tags": [], "wantsTranslation": false, "totalSubmit": 411, "totalAccepted": 176, "flag": 5, "pid": "CF807A", "title": "Is it rated?", "difficulty": 3, "fullScore": 100, "type": "CF"}, {"tags": [], "wantsTranslation": false, "totalSubmit": 28, "totalAccepted": 15, "flag": 5, "pid": "CF807B", "title": "T-Shirt Hunt", "difficulty": 3, "fullScore": 100, "type": "CF"}, {"tags": [], "wantsTranslation": false, "totalSubmit": 465, "totalAccepted": 106, "flag": 5, "pid": "CF808A", "title": "Lucky Year", "difficulty": 2, "fullScore": 100, "type": "CF"}, {"tags": [], "wantsTranslation": false, "totalSubmit": 337, "totalAccepted": 90, "flag": 5, "pid": "CF808B", "title": "Average Sleep Time", "difficulty": 2, "fullScore": 100, "type": "CF"}, {"tags": [], "wantsTranslation": false, "totalSubmit": 740, "totalAccepted": 192, "flag": 5, "pid": "CF808C", "title": "Tea Party", "difficulty": 3, "fullScore": 100, "type": "CF"}, {"tags": [], "wantsTranslation": false, "totalSubmit": 1263, "totalAccepted": 261, "flag": 5, "pid": "CF808D", "title": "Array Division", "difficulty": 4, "fullScore": 100, "type": "CF"}, {"tags": [3, 45], "wantsTranslation": false, "totalSubmit": 1183, "totalAccepted": 333, "flag": 5, "pid": "CF808E", "title": "Selling Souvenirs", "difficulty": 6, "fullScore": 100, "type": "CF"}, {"tags": [], "wantsTranslation": false, "totalSubmit": 689, "totalAccepted": 258, "flag": 5, "pid": "CF808F", "title": "Card Game", "difficulty": 6, "fullScore": 100, "type": "CF"}, {"tags": [], "wantsTranslation": false, "totalSubmit": 2724, "totalAccepted": 991, "flag": 5, "pid": "CF808G", "title": "Anthem of Berland", "difficulty": 6, "fullScore": 100, "type": "CF"}, {"tags": [], "wantsTranslation": false, "totalSubmit": 212, "totalAccepted": 105, "flag": 5, "pid": "CF809A", "title": "Do you want a date?", "difficulty": 4, "fullScore": 100, "type": "CF"}, {"tags": [], "wantsTranslation": false, "totalSubmit": 110, "totalAccepted": 53, "flag": 5, "pid": "CF809B", "title": "Glad to see you!", "difficulty": 5, "fullScore": 100, "type": "CF"}, {"tags": [], "wantsTranslation": false, "totalSubmit": 322, "totalAccepted": 159, "flag": 5, "pid": "CF809C", "title": "Find a car", "difficulty": 6, "fullScore": 100, "type": "CF"}, {"tags": [3, 50, 111], "wantsTranslation": false, "totalSubmit": 1593, "totalAccepted": 492, "flag": 5, "pid": "CF809D", "title": "Hitchhiking in the Baltic States", "difficulty": 6, "fullScore": 100, "type": "CF"}, {"tags": [], "wantsTranslation": false, "totalSubmit": 1472, "totalAccepted": 542, "flag": 5, "pid": "CF809E", "title": "Surprise me!", "difficulty": 6, "fullScore": 100, "type": "CF"}, {"tags": [], "wantsTranslation": false, "totalSubmit": 566, "totalAccepted": 301, "flag": 5, "pid": "CF810A", "title": "Straight \u00abA\u00bb", "difficulty": 2, "fullScore": 100, "type": "CF"}, {"tags": [], "wantsTranslation": false, "totalSubmit": 321, "totalAccepted": 129, "flag": 5, "pid": "CF810B", "title": "Summer sell-off", "difficulty": 3, "fullScore": 100, "type": "CF"}, {"tags": [], "wantsTranslation": false, "totalSubmit": 518, "totalAccepted": 198, "flag": 5, "pid": "CF811A", "title": "Vladik and Courtesy", "difficulty": 2, "fullScore": 100, "type": "CF"}, {"tags": [111], "wantsTranslation": false, "totalSubmit": 95, "totalAccepted": 45, "flag": 5, "pid": "CF811B", "title": "Vladik and Complicated Book", "difficulty": 2, "fullScore": 100, "type": "CF"}, {"tags": [], "wantsTranslation": false, "totalSubmit": 108, "totalAccepted": 51, "flag": 5, "pid": "CF811C", "title": "Vladik and Memorable Trip", "difficulty": 4, "fullScore": 100, "type": "CF"}, {"tags": [103], "wantsTranslation": true, "totalSubmit": 43, "totalAccepted": 23, "flag": 5, "pid": "CF811D", "title": "Vladik and Favorite Game", "difficulty": 5, "fullScore": 100, "type": "CF"}, {"tags": [], "wantsTranslation": false, "totalSubmit": 480, "totalAccepted": 205, "flag": 5, "pid": "CF811E", "title": "Vladik and Entertaining Flags", "difficulty": 6, "fullScore": 100, "type": "CF"}, {"tags": [], "wantsTranslation": false, "totalSubmit": 48, "totalAccepted": 24, "flag": 5, "pid": "CF812A", "title": "Sagheer and Crossroads", "difficulty": 2, "fullScore": 100, "type": "CF"}, {"tags": [], "wantsTranslation": false, "totalSubmit": 291, "totalAccepted": 67, "flag": 5, "pid": "CF812B", "title": "Sagheer, the Hausmeister", "difficulty": 3, "fullScore": 100, "type": "CF"}, {"tags": [], "wantsTranslation": false, "totalSubmit": 434, "totalAccepted": 172, "flag": 5, "pid": "CF812C", "title": "Sagheer and Nubian Market", "difficulty": 3, "fullScore": 100, "type": "CF"}]