[{"tags": [], "wantsTranslation": false, "totalSubmit": 679, "totalAccepted": 373, "flag": 5, "pid": "CF1204C", "title": "Anna, Svyatoslav and Maps", "difficulty": 4, "fullScore": 100, "type": "CF"}, {"tags": [], "wantsTranslation": false, "totalSubmit": 246, "totalAccepted": 185, "flag": 5, "pid": "CF1204D1", "title": "Kirk and a Binary String (easy version)", "difficulty": 4, "fullScore": 100, "type": "CF"}, {"tags": [], "wantsTranslation": false, "totalSubmit": 289, "totalAccepted": 214, "flag": 5, "pid": "CF1204D2", "title": "Kirk and a Binary String (hard version)", "difficulty": 5, "fullScore": 100, "type": "CF"}, {"tags": [], "wantsTranslation": false, "totalSubmit": 1005, "totalAccepted": 486, "flag": 5, "pid": "CF1204E", "title": "Natasha, Sasha and the Prefix Sums", "difficulty": 6, "fullScore": 100, "type": "CF"}, {"tags": [], "wantsTranslation": false, "totalSubmit": 408, "totalAccepted": 265, "flag": 5, "pid": "CF1205A", "title": "Almost Equal", "difficulty": 3, "fullScore": 100, "type": "CF"}, {"tags": [], "wantsTranslation": false, "totalSubmit": 1565, "totalAccepted": 462, "flag": 5, "pid": "CF1205B", "title": "Shortest Cycle", "difficulty": 5, "fullScore": 100, "type": "CF"}, {"tags": [], "wantsTranslation": false, "totalSubmit": 232, "totalAccepted": 84, "flag": 5, "pid": "CF1205C", "title": "Palindromic Paths", "difficulty": 6, "fullScore": 100, "type": "CF"}, {"tags": [], "wantsTranslation": false, "totalSubmit": 325, "totalAccepted": 154, "flag": 5, "pid": "CF1205D", "title": "Almost All", "difficulty": 6, "fullScore": 100, "type": "CF"}, {"tags": [], "wantsTranslation": false, "totalSubmit": 161, "totalAccepted": 116, "flag": 5, "pid": "CF1205E", "title": "Expected Value Again", "difficulty": 7, "fullScore": 100, "type": "CF"}, {"tags": [], "wantsTranslation": false, "totalSubmit": 98, "totalAccepted": 42, "flag": 5, "pid": "CF1205F", "title": "Beauty of a Permutation", "difficulty": 7, "fullScore": 100, "type": "CF"}, {"tags": [], "wantsTranslation": false, "totalSubmit": 474, "totalAccepted": 306, "flag": 5, "pid": "CF1206A", "title": "Choose Two Numbers", "difficulty": 1, "fullScore": 100, "type": "CF"}, {"tags": [], "wantsTranslation": false, "totalSubmit": 563, "totalAccepted": 284, "flag": 5, "pid": "CF1206B", "title": "Make Product Equal One", "difficulty": 2, "fullScore": 100, "type": "CF"}, {"tags": [], "wantsTranslation": false, "totalSubmit": 383, "totalAccepted": 280, "flag": 5, "pid": "CF1207A", "title": "There Are Two Types Of Burgers", "difficulty": 1, "fullScore": 100, "type": "CF"}, {"tags": [], "wantsTranslation": false, "totalSubmit": 385, "totalAccepted": 216, "flag": 5, "pid": "CF1207B", "title": "Square Filling", "difficulty": 2, "fullScore": 100, "type": "CF"}, {"tags": [], "wantsTranslation": false, "totalSubmit": 856, "totalAccepted": 366, "flag": 5, "pid": "CF1207C", "title": "Gas Pipeline", "difficulty": 3, "fullScore": 100, "type": "CF"}, {"tags": [], "wantsTranslation": false, "totalSubmit": 584, "totalAccepted": 243, "flag": 5, "pid": "CF1207D", "title": "Number Of Permutations", "difficulty": 4, "fullScore": 100, "type": "CF"}, {"tags": [], "wantsTranslation": false, "totalSubmit": 774, "totalAccepted": 339, "flag": 5, "pid": "CF1207E", "title": "XOR Guessing", "difficulty": 5, "fullScore": 100, "type": "CF"}, {"tags": [], "wantsTranslation": false, "totalSubmit": 4508, "totalAccepted": 1361, "flag": 5, "pid": "CF1207F", "title": "Remainder Problem", "difficulty": 5, "fullScore": 100, "type": "CF"}, {"tags": [], "wantsTranslation": false, "totalSubmit": 937, "totalAccepted": 470, "flag": 5, "pid": "CF1207G", "title": "Indie Album", "difficulty": 6, "fullScore": 100, "type": "CF"}, {"tags": [], "wantsTranslation": false, "totalSubmit": 432, "totalAccepted": 255, "flag": 5, "pid": "CF1208A", "title": "XORinacci", "difficulty": 2, "fullScore": 100, "type": "CF"}, {"tags": [], "wantsTranslation": false, "totalSubmit": 358, "totalAccepted": 143, "flag": 5, "pid": "CF1208B", "title": "Uniqueness", "difficulty": 3, "fullScore": 100, "type": "CF"}, {"tags": [], "wantsTranslation": false, "totalSubmit": 305, "totalAccepted": 187, "flag": 5, "pid": "CF1208C", "title": "Magic Grid", "difficulty": 3, "fullScore": 100, "type": "CF"}, {"tags": [], "wantsTranslation": false, "totalSubmit": 672, "totalAccepted": 272, "flag": 5, "pid": "CF1208D", "title": "Restore Permutation", "difficulty": 4, "fullScore": 100, "type": "CF"}, {"tags": [], "wantsTranslation": false, "totalSubmit": 509, "totalAccepted": 178, "flag": 5, "pid": "CF1208E", "title": "Let Them Slide", "difficulty": 5, "fullScore": 100, "type": "CF"}, {"tags": [], "wantsTranslation": false, "totalSubmit": 1657, "totalAccepted": 680, "flag": 5, "pid": "CF1208F", "title": "Bits And Pieces", "difficulty": 6, "fullScore": 100, "type": "CF"}, {"tags": [], "wantsTranslation": false, "totalSubmit": 387, "totalAccepted": 218, "flag": 5, "pid": "CF1208G", "title": "Polygons", "difficulty": 6, "fullScore": 100, "type": "CF"}, {"tags": [], "wantsTranslation": false, "totalSubmit": 163, "totalAccepted": 56, "flag": 5, "pid": "CF1208H", "title": "Red Blue Tree", "difficulty": 7, "fullScore": 100, "type": "CF"}, {"tags": [], "wantsTranslation": false, "totalSubmit": 541, "totalAccepted": 339, "flag": 5, "pid": "CF1209A", "title": "Paint the Numbers", "difficulty": 2, "fullScore": 100, "type": "CF"}, {"tags": [], "wantsTranslation": false, "totalSubmit": 456, "totalAccepted": 146, "flag": 5, "pid": "CF1209B", "title": "Koala and Lights", "difficulty": 2, "fullScore": 100, "type": "CF"}, {"tags": [], "wantsTranslation": false, "totalSubmit": 336, "totalAccepted": 183, "flag": 5, "pid": "CF1209C", "title": "Paint the Digits", "difficulty": 4, "fullScore": 100, "type": "CF"}, {"tags": [], "wantsTranslation": false, "totalSubmit": 1835, "totalAccepted": 985, "flag": 5, "pid": "CF1209D", "title": "Cow and Snacks", "difficulty": 3, "fullScore": 100, "type": "CF"}, {"tags": [], "wantsTranslation": false, "totalSubmit": 793, "totalAccepted": 454, "flag": 5, "pid": "CF1209E1", "title": "Rotate Columns (easy version)", "difficulty": 5, "fullScore": 100, "type": "CF"}, {"tags": [], "wantsTranslation": false, "totalSubmit": 1582, "totalAccepted": 597, "flag": 5, "pid": "CF1209E2", "title": "Rotate Columns (hard version)", "difficulty": 6, "fullScore": 100, "type": "CF"}, {"tags": [], "wantsTranslation": false, "totalSubmit": 1071, "totalAccepted": 297, "flag": 5, "pid": "CF1209F", "title": "Koala and Notebook", "difficulty": 6, "fullScore": 100, "type": "CF"}, {"tags": [], "wantsTranslation": false, "totalSubmit": 364, "totalAccepted": 254, "flag": 5, "pid": "CF1209G1", "title": "Into Blocks (easy version)", "difficulty": 5, "fullScore": 100, "type": "CF"}, {"tags": [], "wantsTranslation": false, "totalSubmit": 503, "totalAccepted": 239, "flag": 5, "pid": "CF1209G2", "title": "Into Blocks (hard version)", "difficulty": 7, "fullScore": 100, "type": "CF"}, {"tags": [], "wantsTranslation": false, "totalSubmit": 57, "totalAccepted": 36, "flag": 5, "pid": "CF1209H", "title": "Moving Walkways", "difficulty": 7, "fullScore": 100, "type": "CF"}, {"tags": [], "wantsTranslation": false, "totalSubmit": 257, "totalAccepted": 13, "flag": 5, "pid": "CF1211A", "title": "Three Problems", "difficulty": 1, "fullScore": 100, "type": "CF"}, {"tags": [], "wantsTranslation": false, "totalSubmit": 121, "totalAccepted": 4, "flag": 5, "pid": "CF1211B", "title": "Traveling Around the Golden Ring of Berland", "difficulty": 3, "fullScore": 100, "type": "CF"}, {"tags": [], "wantsTranslation": false, "totalSubmit": 54, "totalAccepted": 3, "flag": 5, "pid": "CF1211C", "title": "Ice Cream", "difficulty": 4, "fullScore": 100, "type": "CF"}, {"tags": [], "wantsTranslation": false, "totalSubmit": 22, "totalAccepted": 4, "flag": 5, "pid": "CF1211F", "title": "kotlinkotlinkotlinkotlin...", "difficulty": 5, "fullScore": 100, "type": "CF"}, {"tags": [], "wantsTranslation": false, "totalSubmit": 9, "totalAccepted": 3, "flag": 5, "pid": "CF1211G", "title": "King's Path", "difficulty": 6, "fullScore": 100, "type": "CF"}, {"tags": [], "wantsTranslation": false, "totalSubmit": 5, "totalAccepted": 1, "flag": 5, "pid": "CF1211H", "title": "Road Repair in Treeland", "difficulty": 7, "fullScore": 100, "type": "CF"}, {"tags": [], "wantsTranslation": false, "totalSubmit": 584, "totalAccepted": 317, "flag": 5, "pid": "CF1213A", "title": "Chips Moving", "difficulty": 1, "fullScore": 100, "type": "CF"}, {"tags": [], "wantsTranslation": false, "totalSubmit": 644, "totalAccepted": 289, "flag": 5, "pid": "CF1213B", "title": "Bad Prices", "difficulty": 2, "fullScore": 100, "type": "CF"}, {"tags": [], "wantsTranslation": false, "totalSubmit": 458, "totalAccepted": 222, "flag": 5, "pid": "CF1213C", "title": "Book Reading", "difficulty": 3, "fullScore": 100, "type": "CF"}, {"tags": [], "wantsTranslation": false, "totalSubmit": 467, "totalAccepted": 253, "flag": 5, "pid": "CF1213D1", "title": "Equalizing by Division (easy version)", "difficulty": 3, "fullScore": 100, "type": "CF"}, {"tags": [], "wantsTranslation": false, "totalSubmit": 496, "totalAccepted": 270, "flag": 5, "pid": "CF1213D2", "title": "Equalizing by Division (hard version)", "difficulty": 4, "fullScore": 100, "type": "CF"}, {"tags": [], "wantsTranslation": false, "totalSubmit": 282, "totalAccepted": 142, "flag": 5, "pid": "CF1213E", "title": "Two Small Strings", "difficulty": 5, "fullScore": 100, "type": "CF"}, {"tags": [], "wantsTranslation": false, "totalSubmit": 744, "totalAccepted": 257, "flag": 5, "pid": "CF1213F", "title": "Unstable String Sort", "difficulty": 6, "fullScore": 100, "type": "CF"}]